cbrlib/__init__.py
cbrlib/casebase.py
cbrlib/evaluate.py
cbrlib/facetting.py
cbrlib/types.py
cbrlib-2.0.10.dist-info/LICENSE
cbrlib-2.0.10.dist-info/METADATA
cbrlib-2.0.10.dist-info/WHEEL
cbrlib-2.0.10.dist-info/RECORD
